esme/__init__.py
esme-0.0.0.dev0.dist-info/METADATA
esme-0.0.0.dev0.dist-info/WHEEL
esme-0.0.0.dev0.dist-info/top_level.txt
esme-0.0.0.dev0.dist-info/RECORD
